odoo/addons/ssi_sale_order_state_change_constrain/README.rst
odoo/addons/ssi_sale_order_state_change_constrain/__init__.py
odoo/addons/ssi_sale_order_state_change_constrain/__manifest__.py
odoo/addons/ssi_sale_order_state_change_constrain/models/__init__.py
odoo/addons/ssi_sale_order_state_change_constrain/models/sale_order.py
odoo/addons/ssi_sale_order_state_change_constrain/static/description/icon.png
odoo14_addon_ssi_sale_order_state_change_constrain-14.0.1.2.0.dist-info/METADATA
odoo14_addon_ssi_sale_order_state_change_constrain-14.0.1.2.0.dist-info/WHEEL
odoo14_addon_ssi_sale_order_state_change_constrain-14.0.1.2.0.dist-info/top_level.txt
odoo14_addon_ssi_sale_order_state_change_constrain-14.0.1.2.0.dist-info/RECORD
